photosapi_client/__init__.py
photosapi_client/client.py
photosapi_client/errors.py
photosapi_client/py.typed
photosapi_client/types.py
photosapi_client/api/__init__.py
photosapi_client/api/default/__init__.py
photosapi_client/api/default/album_create_albums_post.py
photosapi_client/api/default/album_delete_album_id_delete.py
photosapi_client/api/default/album_find_albums_get.py
photosapi_client/api/default/album_patch_albums_id_patch.py
photosapi_client/api/default/album_put_albums_id_put.py
photosapi_client/api/default/login_for_access_token_token_post.py
photosapi_client/api/default/photo_delete_photos_id_delete.py
photosapi_client/api/default/photo_find_albums_album_photos_get.py
photosapi_client/api/default/photo_get_photos_id_get.py
photosapi_client/api/default/photo_get_token_token_photo_token_get.py
photosapi_client/api/default/photo_move_photos_id_put.py
photosapi_client/api/default/photo_patch_photos_id_patch.py
photosapi_client/api/default/photo_random_albums_album_photos_random_get.py
photosapi_client/api/default/photo_upload_albums_album_photos_post.py
photosapi_client/api/default/user_confirm_users_user_confirm_get.py
photosapi_client/api/default/user_confirm_users_user_confirm_patch.py
photosapi_client/api/default/user_create_users_post.py
photosapi_client/api/default/user_delete_users_me_delete.py
photosapi_client/api/default/user_me_users_me_get.py
photosapi_client/api/default/video_delete_videos_id_delete.py
photosapi_client/api/default/video_find_albums_album_videos_get.py
photosapi_client/api/default/video_get_videos_id_get.py
photosapi_client/api/default/video_move_videos_id_put.py
photosapi_client/api/default/video_patch_videos_id_patch.py
photosapi_client/api/default/video_random_albums_album_videos_random_get.py
photosapi_client/api/default/video_upload_albums_album_videos_post.py
photosapi_client/models/__init__.py
photosapi_client/models/album.py
photosapi_client/models/album_modified.py
PhotosAPI_Client-0.6.0.dist-info/METADATA
PhotosAPI_Client-0.6.0.dist-info/WHEEL
PhotosAPI_Client-0.6.0.dist-info/top_level.txt
PhotosAPI_Client-0.6.0.dist-info/RECORD
