Metadata-Version: 2.1
Name: PhotosAPI_Client
Version: 0.6.0
Summary: A client library for accessing Photos API
Requires-Python: >=3.7, <4
Requires-Dist: httpx <0.24.0,>=0.15.0
Requires-Dist: attrs >=21.3.0
Requires-Dist: python-dateutil <3,>=2.8.0
